{"external_width":{"type":"float"},"cover_wall_thickness":{"type":"float"},"cover_internal_margin":{"type":"float"},"cover_printing_y_offset":{"type":"float"},"external_length":{"type":"float"},"cover_internal_height":{"type":"float"},"external_corner_radius":{"type":"float"},"part_selector":{"values":["1","2","3"],"type":"enum"},"bottom_thickness":{"type":"float"},"cover_external_height":{"type":"float"},"cover_thickness":{"type":"float"},"wall_thickness":{"type":"float"},"base_height":{"type":"float"}}