{"frame_width":{"end":50.0,"step":1,"type":"range","start":15.0},"picture_height":{"end":250.0,"step":1,"type":"range","start":100.0},"stand_tilt":{"values":["15","20","25","30","35","40","45"],"type":"enum"},"frame_depth":{"end":10.0,"step":1,"type":"range","start":5.0},"frame_thickness":{"end":50.0,"step":1,"type":"range","start":15.0},"stand":{"values":["yes","no"],"type":"enum"},"frame_lip":{"end":10.0,"step":1,"type":"range","start":5.0},"picture_width":{"end":250.0,"step":1,"type":"range","start":100.0}}