{"pi":{"type":"float"},"tslot_width1":{"type":"float"},"scallop_radius":{"type":"float"},"stator_thickness":{"type":"float"},"$fn":{"type":"float"},"endplate_thickness":{"type":"float"},"armature_spindle_radius":{"type":"float"},"form_thickness":{"type":"float"},"armature_spindle_clearance":{"type":"float"},"tslot_width2":{"type":"float"},"tslot_height1":{"type":"float"},"armature_radius":{"type":"float"},"armature_clearance":{"type":"float"},"tslot_height2":{"type":"float"},"tslot_carrier_thickness":{"type":"float"},"armature_length":{"type":"float"},"armature_spindle_length":{"type":"float"},"tslot_clearance":{"type":"float"}}