{"ChipValue":{"type":"float"},"part":{"values":["single","dual"],"type":"enum"},"width":{"type":"float"},"CasinofontName":{"values":["\"write\/Letters.dxf\""," \"write\/BlackRose.dxf\""," \"write\/orbitron.dxf\""," \"write\/knewave.dxf\""," \"write\/braille.dxf\""],"type":"enum"},"CasinoName":{"type":"string"},"Thickness":{"type":"float"},"CasinoNameHeight":{"type":"float"},"ValueHeight":{"type":"float"},"ValuefontName":{"values":["\"write\/Letters.dxf\""," \"write\/BlackRose.dxf\""," \"write\/orbitron.dxf\""," \"write\/knewave.dxf\""," \"write\/braille.dxf\""],"type":"enum"},"Diameter":{"type":"float"}}