{"Mounting_screw_thread_diameter":{"type":"float"},"Head_diameter_mounting_screw":{"type":"float"},"Ring_or_segment":{"values":["0","1"],"type":"enum"},"Rods_and_rings_wide":{"type":"float"},"Distance_between_mounting_holes":{"type":"float"},"Number_of_rings":{"end":15.0,"step":1,"type":"range","start":1.0},"Solid_center":{"values":["1","0"],"type":"enum"},"Height_of_the_cone_mounting_screw":{"type":"float"},"Drop_or_ring":{"values":["0","1"],"type":"enum"},"Thickness_of_the_plate":{"type":"float"},"External_dimension":{"type":"float"}}