{"part":{"type":"string"},"itterations":{"end":10.0,"step":1,"type":"range","start":1.0},"workingEndSlope":{"end":15.0,"step":0.5,"type":"range","start":0.0},"wallThickness":{"end":5.0,"step":0.1,"type":"range","start":0.5},"bitDepth":{"type":"float"},"step":{"type":"float"},"handleLength":{"type":"float"},"startFlat":{"type":"float"},"thickness":{"type":"float"},"bitFlats":{"end":7.0,"step":0.01,"type":"range","start":6.3},"toolDepth":{"type":"float"},"handleRoundness":{"end":5.0,"step":0.25,"type":"range","start":0.0},"bitHoles":{"values":["1"," 5"," 9"," 13"," 17"],"type":"enum"}}