{"foot_count":{"end":30.0,"step":1,"type":"range","start":2.0},"washer_diameter":{"end":100.0,"step":1,"type":"range","start":0.1},"nut_diameter":{"end":100.0,"step":1,"type":"range","start":0.1},"hole_diameter":{"end":100.0,"step":1,"type":"range","start":0.1},"wall_thickness":{"end":20.0,"step":1,"type":"range","start":1.0},"foot_distance":{"end":5000.0,"step":1,"type":"range","start":1.0},"light":{"values":["0","1"],"type":"enum"},"center_diameter":{"end":100.0,"step":1,"type":"range","start":1.0},"foot_diameter":{"end":250.0,"step":1,"type":"range","start":1.0},"foot_connector_thickness":{"end":100.0,"step":1,"type":"range","start":3.0}}