{"stencil_pattern_element_rotation":{"end":180.0,"step":1,"type":"range","start":0.0},"phone_model":{"values":["3"," 2"," 1"," 0"],"type":"enum"},"stencil_vertical_position":{"end":100.0,"step":1,"type":"range","start":0.0},"custom_back_camera_y_position":{"type":"float"},"input":{"type":"string"},"stencil_shape":{"values":["1","2","3","4","5","6","7","0"],"type":"enum"},"custom_bottom_fillet_resolution":{"type":"float"},"pattern_element_overlap":{"end":100.0,"step":1,"type":"range","start":0.0},"stencil_pattern_element_overlap":{"end":100.0,"step":1,"type":"range","start":0.0},"stencil_size":{"end":100.0,"step":1,"type":"range","start":10.0},"custom_bottom_fillet_radius":{"type":"float"},"custom_back_camera_x_size":{"type":"float"},"pattern_line_thickness":{"end":50.0,"step":1,"type":"range","start":0.0},"stencil_mirror":{"values":["0"," 1"],"type":"enum"},"custom_bottom_port_corner_resolution":{"type":"float"},"custom_corner_resolution":{"type":"float"},"stencil_pattern_line_thickness":{"end":50.0,"step":1,"type":"range","start":0.0},"custom_bottom_port_x_position":{"type":"float"},"custom_phone_width":{"type":"float"},"custom_right_port_corner_radius":{"type":"float"},"custom_corner_radius":{"type":"float"},"stencil_pattern_element_shape":{"values":["3","4","5","6","7","8","9","10","11","12","30"],"type":"enum"},"custom_left_port_length":{"type":"float"},"custom_top_port_x_position":{"type":"float"},"custom_back_extra_port_y_position":{"type":"float"},"custom_back_extra_port_y_size":{"type":"float"},"stencil_rotation":{"end":360.0,"step":1,"type":"range","start":0.0},"custom_bottom_outer_edge_chamfer_radius":{"type":"float"},"custom_top_port_length":{"type":"float"},"custom_left_port_corner_radius":{"type":"float"},"custom_phone_thickness":{"type":"float"},"custom_back_camera_x_position":{"type":"float"},"custom_right_port_corner_resolution":{"type":"float"},"printer_tolerance":{"values":["0.2","0.25","0.3","0.35","0.4","0.45","0.5","0.55","0.6","0.65","0.7","0.75","0.8","0.85","0.9","0.95","1"],"type":"enum"},"custom_top_port_corner_resolution":{"type":"float"},"custom_overhang_thickness":{"type":"float"},"custom_overhang_width":{"type":"float"},"custom_bottom_port_corner_radius":{"type":"float"},"use_mouse_ears":{"values":["0","1"],"type":"enum"},"custom_bottom_port_length":{"type":"float"},"custom_right_port_length":{"type":"float"},"pattern_element_radius":{"end":22.0,"step":1,"type":"range","start":4.0},"custom_case_wall_thickness":{"type":"float"},"custom_top_inner_edge_chamfer_radius":{"type":"float"},"custom_back_extra_port_corner_radius":{"type":"float"},"custom_back_camera_y_size":{"type":"float"},"custom_right_port_y_position":{"type":"float"},"custom_phone_length":{"type":"float"},"custom_back_extra_port_corner_resolution":{"type":"float"},"custom_case_pattern_thickness":{"type":"float"},"custom_back_extra_port_x_position":{"type":"float"},"stencil_horizontal_position":{"end":100.0,"step":1,"type":"range","start":0.0},"custom_back_camera_corner_radius":{"type":"float"},"stencil_fill_type":{"values":["0","1","2"],"type":"enum"},"pattern_element_rotation":{"end":180.0,"step":1,"type":"range","start":0.0},"use_custom_dimensions":{"values":["0","1"],"type":"enum"},"stencil_pattern_element_radius":{"end":22.0,"step":1,"type":"range","start":6.0},"custom_left_port_corner_resolution":{"type":"float"},"custom_back_camera_corner_resolution":{"type":"float"},"use_pattern":{"values":["0","1"],"type":"enum"},"use_stencil":{"values":["0","1"],"type":"enum"},"custom_left_port_y_position":{"type":"float"},"custom_top_outer_edge_chamfer_radius":{"type":"float"},"custom_top_port_corner_radius":{"type":"float"},"pattern_element_shape":{"values":["3","4","5","6","7","8","9","10","11","12","30"],"type":"enum"},"custom_overhang_fillet_resolution":{"type":"float"},"custom_back_extra_port_x_size":{"type":"float"}}