{"twist_cycles":{"end":6.0,"step":1,"type":"range","start":0.0},"ruffle_depth":{"end":8.0,"step":1,"type":"range","start":1.0},"smoothing_cycles":{"end":6.0,"step":1,"type":"range","start":0.0},"radial_resolution":{"type":"float"},"height":{"end":100.0,"step":1,"type":"range","start":10.0},"waist_diameter":{"end":100.0,"step":1,"type":"range","start":10.0},"base_diameter":{"end":100.0,"step":1,"type":"range","start":10.0},"ruffle_count":{"end":12.0,"step":1,"type":"range","start":2.0},"twist_max":{"end":90.0,"step":1,"type":"range","start":-90.0},"display_diameters":{"values":["0"," 1"],"type":"enum"},"vertical_resolution":{"type":"float"},"top_diameter":{"end":100.0,"step":1,"type":"range","start":10.0},"neck_diameter":{"end":100.0,"step":1,"type":"range","start":10.0},"smoothing_start":{"end":100.0,"step":1,"type":"range","start":0.0}}